langchain_astradb-1.0.0.dist-info/METADATA
langchain_astradb-1.0.0.dist-info/WHEEL
langchain_astradb-1.0.0.dist-info/entry_points.txt
langchain_astradb-1.0.0.dist-info/licenses/LICENSE
langchain_astradb/__init__.py
langchain_astradb/cache.py
langchain_astradb/chat_message_histories.py
langchain_astradb/document_loaders.py
langchain_astradb/py.typed
langchain_astradb/storage.py
langchain_astradb/utils/__init__.py
langchain_astradb/utils/astradb.py
langchain_astradb/utils/vector_store_autodetect.py
langchain_astradb/utils/vector_store_codecs.py
langchain_astradb/vectorstores.py
langchain_astradb-1.0.0.dist-info/RECORD
