Metadata-Version: 2.1
Name: langchain-astradb
Version: 1.0.0
Summary: An integration package connecting Astra DB and LangChain
License: MIT
Project-URL: Source Code, https://github.com/langchain-ai/langchain-datastax/tree/main/libs/astradb
Project-URL: repository, https://github.com/langchain-ai/langchain-datastax
Requires-Python: <4.0.0,>=3.10.0
Requires-Dist: langchain-core<2.0.0,>=0.3.74
Requires-Dist: astrapy<3.0.0,>=2.0.1
Requires-Dist: numpy>=1.21
Requires-Dist: numpy>=1.26; python_version >= "3.12"
Requires-Dist: numpy>=2.1.0; python_version >= "3.13"
